anscombe_transform/__init__.py
anscombe_transform/codec.py
anscombe_transform/estimate.py
anscombe_transform/version.py
anscombe_transform-1.0.0.dist-info/METADATA
anscombe_transform-1.0.0.dist-info/WHEEL
anscombe_transform-1.0.0.dist-info/licenses/LICENSE
anscombe_transform-1.0.0.dist-info/RECORD
