Metadata-Version: 2.4
Name: anscombe_transform
Version: 1.0.0
Summary: Zarr V2 and V3 codecs for compressing photon-limited movies.
Project-URL: Homepage, https://github.com/datajoint/anscombe-transform
Project-URL: Source, https://github.com/datajoint/anscombe-transform
Project-URL: Issues, https://github.com/datajoint/anscombe-transform/issues
Author-email: Jerome Lecoq <jeromel@alleninstitute.org>, Dimitri Yatsenko <dimitr@datajoint.com>, Davis Bennett <davis.v.bennett@gmail.com>
Maintainer-email: Dimitri Yatsenko <dimitr@datajoint.com>
License: MIT License
License-File: LICENSE
Keywords: compression algorithms,multimedia,multiphoton microscopy,numcodecs,video compression,zarr
Classifier: License :: OSI Approved :: MIT License
Classifier: Operating System :: OS Independent
Classifier: Programming Language :: Python :: 3
Classifier: Topic :: Multimedia :: Video
Classifier: Topic :: Software Development :: Libraries
Requires-Python: >=3.11
Requires-Dist: scikit-learn
Requires-Dist: zarr>=3.1.2
Provides-Extra: docs
Requires-Dist: griffe-inherited-docstrings; extra == 'docs'
Requires-Dist: markdown-exec[ansi]; extra == 'docs'
Requires-Dist: mike>=2.1.3; extra == 'docs'
Requires-Dist: mkdocs-material[imaging]>=9.6.14; extra == 'docs'
Requires-Dist: mkdocs-redirects>=1.2.0; extra == 'docs'
Requires-Dist: mkdocs>=1.6.1; extra == 'docs'
Requires-Dist: mkdocstrings-python>=1.16.10; extra == 'docs'
Requires-Dist: mkdocstrings>=0.29.1; extra == 'docs'
Provides-Extra: test
Requires-Dist: imageio; extra == 'test'
Requires-Dist: matplotlib; extra == 'test'
Requires-Dist: nbmake; extra == 'test'
Requires-Dist: pytest-cov; extra == 'test'
Requires-Dist: pytest==8.4.2; extra == 'test'
Requires-Dist: scipy; extra == 'test'
